README.rst
codicefiscale.py
setup.py
codicefiscale.egg-info/PKG-INFO
codicefiscale.egg-info/SOURCES.txt
codicefiscale.egg-info/dependency_links.txt
codicefiscale.egg-info/top_level.txt
codicefiscale.egg-info/zip-safe