Metadata-Version: 1.1
Name: codicefiscale
Version: 0.9
Summary: Python library for Italian fiscal code (codicefiscale)
Home-page: https://github.com/ema/pycodicefiscale
Author: Emanuele Rocca
Author-email: ema@linux.it
License: LGPL
Download-URL: https://github.com/ema/pycodicefiscale/downloads
Platform: UNKNOWN
